{
  "collapseTableOfContents": false,
  "items": [
    {
      "type": "divider",
      "title": "🌱 Introduction"
    },
    {
      "type": "item",
      "title": "Overview",
      "uri": "/docs/Introduction/Overview.md"
    },
    {
      "type": "item",
      "title": "Getting API Access",
      "uri": "https://docs.roller.app/docs/roller-api/branches/main/qc5cvegxcl1cy"
    },
    {
      "type": "item",
      "title": "Environments",
      "uri": "https://docs.roller.app/docs/roller-api/branches/main/a9y16c1v2unac"
    },
    {
      "type": "item",
      "title": "Authentication",
      "uri": "https://docs.roller.app/docs/roller-api/branches/main/501c2cc6476da"
    },
    {
      "type": "item",
      "title": "Rate Limits & Throttling [Rest API]",
      "uri": "/docs/Introduction/RateLimitsAndThrottling_RestApi.md"
    },
    {
      "type": "item",
      "title": "Changelog",
      "uri": "https://docs.roller.app/docs/roller-api/iglgjf34psufs"
    },
    {
      "type": "divider",
      "title": "🧠 Core Concepts"
    },
    {
      "type": "item",
      "title": "Formatting",
      "uri": "https://docs.roller.app/docs/roller-api/branches/main/nsncpipa2ghoi"
    },
    {
      "type": "item",
      "title": "Booking Limitations",
      "uri": "docs/Introduction/BookingLimitations.md"
    },
    {
      "type": "item",
      "title": "Discounts",
      "uri": "docs/Introduction/Discounts.md"
    },
    {
      "type": "divider",
      "title": "📦 Resources"
    },
    {
      "type": "item",
      "title": "Postman Collection",
      "uri": "https://docs.roller.app/docs/roller-api/branches/main/dhkft63bountn"
    },
    {
      "type": "item",
      "title": "Product Type Mapping",
      "uri": "https://docs.roller.app/docs/roller-api/branches/main/6e4snhv85tuk2"
    },
    {
      "type": "divider",
      "title": "🚀 Use Cases"
    },
    {
      "type": "group",
      "title": "3rd Party Checkout",
      "items": [
        {
          "type": "item",
          "title": "Overview",
          "uri": "/docs/API Use Cases/3rd Party Checkout/ExternalCheckoutOverview.md"
        },
        {
          "type": "item",
          "title": "Checkout Workflow",
          "uri": "/docs/API Use Cases/3rd Party Checkout/CheckoutWorkflow.md"
        },
        {
          "type": "item",
          "title": "Editing or deleting bookings",
          "uri": "/docs/API Use Cases/3rd Party Checkout/EditingOrDeletingBookings.md"
        },
        {
          "type": "item",
          "title": "Managing Refunds",
          "uri": "/docs/API Use Cases/3rd Party Checkout/ManagingRefunds.md"
        }
      ]
    },
    {
      "type": "divider",
      "title": "APIS"
    },
    {
      "type": "item",
      "title": "Rest API Specification",
      "uri": "/reference/Rest-API.v1.yaml"
    },
    {
      "type": "divider",
      "title": "Schemas"
    },
    {
      "type": "item",
      "title": "BookingDetail",
      "uri": "models/BookingDetail.yaml"
    },
    {
      "type": "item",
      "title": "CustomerDetail",
      "uri": "models/CustomerDetail.yaml"
    },
    {
      "type": "item",
      "title": "RedemptionDetail",
      "uri": "models/RedemptionDetail.yaml"
    },
    {
      "type": "item",
      "title": "SignedWaivers",
      "uri": "models/SignedWaivers.yaml"
    },
    {
      "type": "item",
      "title": "PaymentLink",
      "uri": "models/PaymentLink.yaml"
    },
    {
      "type": "item",
      "title": "MembershipDetail",
      "uri": "models/MembershipDetail.yaml"
    },
    {
      "type": "item",
      "title": "CustomerFlag",
      "uri": "models/CustomerFlag.yaml"
    },
    {
      "type": "item",
      "title": "MultiPass",
      "uri": "models/MultiPass.yaml"
    }
  ]
}